odoo/addons/mrp_work_center_component/README.rst
odoo/addons/mrp_work_center_component/__init__.py
odoo/addons/mrp_work_center_component/__manifest__.py
odoo/addons/mrp_work_center_component/i18n/es.po
odoo/addons/mrp_work_center_component/models/__init__.py
odoo/addons/mrp_work_center_component/models/mrp_production.py
odoo/addons/mrp_work_center_component/models/mrp_workcenter.py
odoo/addons/mrp_work_center_component/models/mrp_workorder.py
odoo/addons/mrp_work_center_component/models/stock_move.py
odoo/addons/mrp_work_center_component/readme/CONTRIBUTORS.md
odoo/addons/mrp_work_center_component/readme/DESCRIPTION.md
odoo/addons/mrp_work_center_component/readme/USAGE.md
odoo/addons/mrp_work_center_component/security/ir.model.access.csv
odoo/addons/mrp_work_center_component/static/description/icon.png
odoo/addons/mrp_work_center_component/static/description/index.html
odoo/addons/mrp_work_center_component/tests/__init__.py
odoo/addons/mrp_work_center_component/tests/test_mrp_work_center_components.py
odoo/addons/mrp_work_center_component/views/mrp_production_views.xml
odoo/addons/mrp_work_center_component/views/mrp_workcenter_views.xml
odoo_addon_mrp_work_center_component-17.0.1.0.0.2.dist-info/METADATA
odoo_addon_mrp_work_center_component-17.0.1.0.0.2.dist-info/WHEEL
odoo_addon_mrp_work_center_component-17.0.1.0.0.2.dist-info/top_level.txt
odoo_addon_mrp_work_center_component-17.0.1.0.0.2.dist-info/RECORD
