Metadata-Version: 2.1
Name: odoo-addon-mrp_work_center_component
Version: 17.0.1.0.0.2
Requires-Python: >=3.10
Requires-Dist: odoo>=17.0a,<17.1dev
Summary: Add a Components tab in Work Center form to define needed products and quantities.
Home-page: https://github.com/sygel-technology/sy-manufacture
License: AGPL-3
Author: Sygel
Classifier: Programming Language :: Python
Classifier: Framework :: Odoo
Classifier: Framework :: Odoo :: 17.0
Classifier: License :: OSI Approved :: GNU Affero General Public License v3
